polynomial_unitroot/__init__.py
polynomial_unitroot/critical_values.py
polynomial_unitroot/kernels.py
polynomial_unitroot/simulations.py
polynomial_unitroot/tests.py
polynomial_unitroot/utils.py
polynomial_unitroot-0.0.3.dist-info/METADATA
polynomial_unitroot-0.0.3.dist-info/WHEEL
polynomial_unitroot-0.0.3.dist-info/top_level.txt
polynomial_unitroot-0.0.3.dist-info/RECORD
