Metadata-Version: 2.4
Name: polynomial_unitroot
Version: 0.0.3
Summary: Phillips Unit Root Tests for Polynomials of Integrated Processes
Author-email: Dr Merwan Roudane <merwanroudane920@gmail.com>
Maintainer-email: Dr Merwan Roudane <merwanroudane920@gmail.com>
License: MIT
Project-URL: Homepage, https://github.com/merwanroudane/polyunitroottest
Project-URL: Documentation, https://github.com/merwanroudane/polyunitroottest#readme
Project-URL: Repository, https://github.com/merwanroudane/polyunitroottest
Project-URL: Issues, https://github.com/merwanroudane/polyunitroottest/issues
Project-URL: Changelog, https://github.com/merwanroudane/polyunitroottest/releases
Keywords: econometrics,unit root,time series,integrated processes,Phillips test,cointegration,polynomial transformation,HAC estimation
Classifier: Development Status :: 4 - Beta
Classifier: Intended Audience :: Science/Research
Classifier: Intended Audience :: Developers
Classifier: Intended Audience :: Education
Classifier: License :: OSI Approved :: MIT License
Classifier: Operating System :: OS Independent
Classifier: Programming Language :: Python :: 3
Classifier: Programming Language :: Python :: 3.8
Classifier: Programming Language :: Python :: 3.9
Classifier: Programming Language :: Python :: 3.10
Classifier: Programming Language :: Python :: 3.11
Classifier: Programming Language :: Python :: 3.12
Classifier: Topic :: Scientific/Engineering :: Mathematics
Classifier: Topic :: Scientific/Engineering
Classifier: Typing :: Typed
Requires-Python: >=3.8
Requires-Dist: numpy>=1.20.0
Requires-Dist: scipy>=1.7.0
Provides-Extra: dev
Requires-Dist: pytest>=6.0; extra == "dev"
Requires-Dist: pytest-cov>=2.0; extra == "dev"
Requires-Dist: black>=22.0; extra == "dev"
Requires-Dist: isort>=5.0; extra == "dev"
Requires-Dist: mypy>=0.900; extra == "dev"
Requires-Dist: flake8>=4.0; extra == "dev"
Provides-Extra: docs
Requires-Dist: sphinx>=4.0; extra == "docs"
Requires-Dist: sphinx-rtd-theme>=1.0; extra == "docs"
Requires-Dist: numpydoc>=1.0; extra == "docs"
Provides-Extra: full
Requires-Dist: matplotlib>=3.3.0; extra == "full"
Requires-Dist: pandas>=1.3.0; extra == "full"
Requires-Dist: statsmodels>=0.13.0; extra == "full"
